fstlib/__init__.py
fstlib/fstlib.py
test/__init__.py
test/test.py
test/test2.py
fstlib-1.0.8.dist-info/METADATA
fstlib-1.0.8.dist-info/WHEEL
fstlib-1.0.8.dist-info/top_level.txt
fstlib-1.0.8.dist-info/RECORD
