Metadata-Version: 2.1
Name: fstlib
Version: 1.0.8
Summary: A python library to read fst file. 
Author: Vhiny-Guilley MOMBO
Maintainer: finres team
Requires-Python: >=3.8
Requires-Dist: rpy2
Requires-Dist: pandas
Requires-Dist: numpy
Provides-Extra: dev
Requires-Dist: pytest (>=7.10) ; extra == 'dev'
Requires-Dist: twine (>=4.0.2) ; extra == 'dev'
